{
  "paragraphs": [
    {
      "display": true,
      "person": "Tim Krofecheck<br/>Web Developer",
      "image": "images/mugshot.jpg",
      "text": "Tim is a seasoned Web Developer with 13 years professional experience. Currently he lives in Queens, NY and is working for WebMD as Senior Web Developer since May 2015. Technologies Tim has used at WebMD include HTML5, CSS3, Vanilla JavaScript, Node.js NPM, Grunt, RequireJS, SCSS, jQuery, Handlebars, Omniture (BI) and Akamai AMP Premier. Prior to WebMD, Tim worked at Time Inc as an HTML5 developer utilizing HTML5, CSS3, Vanilla JavaScript, Backbone.js, Handlebars, Underscore.js and Adobe DPS for developing webview storefronts on the iPad, iPhone and Kindle Fire. Tim has also upheld several development roles at the New York Post (Web Developer for 2 years) and at Acxiom Digital (Content Specialist and Solutions Developer for 5 years). While working full-time, Tim has worked as a Freelancer and Contractor on weekends and weeknights to improve his skillset."
    },
    {
      "display": true,
      "name": "Hobbies",
      "text": "video games, on/off/off-off broadway musicals, movies, music, books, building computers, web development"
    },
    {
      "display": true,
      "name": "Interests",
      "text": "Snowball (my cat), cooking, home improvement"
    },
    {
      "display": false,
      "name": "Other activity:",
      "text": "May 23, 2012 - MongoNYC 2012. 10gen conference to discuss non-relational database MongoDB."
    }
  ],
  "copyright": "&copy;2010 &ndash; 2015 Krofecheck.com"
}